azf_wsgi/__init__.py
azf_wsgi/wsgi_adapter.py
azf_wsgi-0.3.1.dist-info/LICENSE
azf_wsgi-0.3.1.dist-info/METADATA
azf_wsgi-0.3.1.dist-info/WHEEL
azf_wsgi-0.3.1.dist-info/top_level.txt
azf_wsgi-0.3.1.dist-info/RECORD
