Metadata-Version: 2.1
Name: azf-wsgi
Version: 0.3.1
Summary: Azure Functions WSGI implementation [deprecated]
Home-page: https://github.com/vtbassmatt/azf-wsgi
Author: Matt Cooper
Author-email: vtbassmatt@gmail.com
License: UNKNOWN
Platform: UNKNOWN
Classifier: Development Status :: 7 - Inactive
Classifier: Environment :: Web Environment
Classifier: Intended Audience :: Developers
Classifier: License :: OSI Approved :: MIT License
Classifier: Programming Language :: Python :: 3.6
Classifier: Topic :: Internet :: WWW/HTTP :: WSGI
Classifier: Topic :: Internet :: WWW/HTTP :: WSGI :: Server
Requires-Dist: azure-functions
